growattRS232/__init__.py
growattRS232/const.py
growattRS232-1.0.0.dist-info/LICENSE
growattRS232-1.0.0.dist-info/METADATA
growattRS232-1.0.0.dist-info/WHEEL
growattRS232-1.0.0.dist-info/top_level.txt
growattRS232-1.0.0.dist-info/RECORD
