Metadata-Version: 2.1
Name: growattRS232
Version: 1.0.0
Summary: Python wrapper for getting data asynchronously from Growatt inverters via serial usb RS232 connection and modbus RTU protocol.
Home-page: https://github.com/ArdescoConsulting/growattRS232
Author: Manuel Stevens
Author-email: manuel.stevens@ardesco.be
License: MIT
Project-URL: Bug Reports, https://github.com/ArdescoConsulting/growattRS232/issues
Project-URL: Source, https://github.com/ArdescoConsulting/growattRS232
Keywords: growatt rs232 modbus
Platform: UNKNOWN
Classifier: Development Status :: 5 - Production/Stable
Classifier: Programming Language :: Python :: 3
Classifier: Programming Language :: Python :: 3.6
Classifier: Programming Language :: Python :: 3.7
Classifier: Programming Language :: Python :: 3.8
Classifier: Programming Language :: Python :: 3 :: Only
Classifier: Operating System :: OS Independent
Classifier: License :: OSI Approved :: MIT License
Classifier: Intended Audience :: Developers
Requires-Python: >=3.6, <4
Requires-Dist: pymodbus
